pybencode/__info__.py
pybencode/__init__.py
pybencode/bencode.py
cpyberry_pybencode-2.0.1.dist-info/LICENSE
cpyberry_pybencode-2.0.1.dist-info/METADATA
cpyberry_pybencode-2.0.1.dist-info/NOTICE
cpyberry_pybencode-2.0.1.dist-info/WHEEL
cpyberry_pybencode-2.0.1.dist-info/top_level.txt
cpyberry_pybencode-2.0.1.dist-info/RECORD
