Metadata-Version: 2.1
Name: cpyberry-pybencode
Version: 2.0.1
Summary: Simple bencode library for python
Home-page: https://github.com/cpyberry/pybencode
Author: cpyberry
Author-email: cpyberry222@gmail.com
License: Apache-2.0 License
Keywords: bencode
Platform: UNKNOWN
Classifier: Development Status :: 5 - Production/Stable
Classifier: Intended Audience :: Developers
Classifier: License :: OSI Approved :: Apache Software License
Classifier: Natural Language :: English
Classifier: Natural Language :: Japanese
Classifier: Programming Language :: Python
Classifier: Programming Language :: Python :: 3
Classifier: Programming Language :: Python :: 3.6
Classifier: Programming Language :: Python :: 3.7
Classifier: Programming Language :: Python :: 3.8
Classifier: Programming Language :: Python :: 3.9
Classifier: Programming Language :: Python :: Implementation
Classifier: Topic :: Software Development :: Libraries :: Python Modules
Requires-Python: >=3.6
